{
  "10299": "long strings of text",
  "10313": "refusal, rejection, denied",
  "10399": "bad and negative descriptors",
  "10456": "size of things",
  "10634": "generating sequences",
  "10813": "preposition followed by the",
  "10830": "had a / have a",
  "11028": "killers, murderers, maintainers, developers",
  "11073": "primacy effect, white coat effect",
  "11084": "serious consequences or penalties",
  "11097": "maximize or achieve goals",
  "11130": "a + positive descriptor",
  "11181": "pronoun me",
  "11286": "one hundred",
  "11328": "could or would be",
  "1133": "agreement and continuation",
  "11391": "if ... were statements",
  "11446": "is not inappropriate or hurtful",
  "1155": "step in processes",
  "11566": "offering products or services",
  "11603": "the [technical noun]",
  "11809": "actions to perform",
  "11816": "going about, to provide",
  "11874": "that arises, satisfaction she",
  "1198": "phrases linking nouns/verbs to prepositions",
  "11983": "wise and smart evaluations",
  "12037": "very + adjective",
  "1217": "do so followed by how/manner",
  "12334": "when to expect",
  "12342": "requires some, captain may, navigate using",
  "12366": "possessive pronouns followed by nouns",
  "12423": "split the file",
  "12477": "possessives and related verbs",
  "12566": "the ethical principles",
  "12745": "leaving or exiting",
  "12826": "verbs followed by it or your",
  "12856": "earn money or rewards",
  "12954": "the number 45",
  "130": "ordering or recommending actions",
  "1308": "in specific situations",
  "13102": "this/the followed by content",
  "13303": "relationship and social connection",
  "13312": "intensifier + adjective",
  "13411": "give up / give way",
  "13427": "sentence and punctuation",
  "13564": "starts clauses introducing contrast",
  "13615": "sentence terminators",
  "1369": "distribution of wealth and power",
  "13721": "small to large, long and happy",
  "13815": "because followed by a reason",
  "13951": "sum of products for game outcomes",
  "14010": "potential harm or offense",
  "14131": "if, ignore, assuming",
  "14161": "significant impact or contribution",
  "14341": "get followed by a noun",
  "14573": "as having, more interested",
  "14703": "could impress",
  "14706": "comma followed by while",
  "14761": "more + descriptive adjective",
  "14908": "\"an\" followed by vowel-starting word",
  "15033": "lead to consequences",
  "15123": "some partial correlation",
  "15169": "adding more information",
  "15708": "things look and seem",
  "15715": "but followed by descriptions of state or action",
  "15777": "inherently good, bad, or malicious",
  "15844": "affirmative or negative continuations",
  "16011": "This number, which implies, represents",
  "16068": "proportion, portion, fraction",
  "1617": "detecting still",
  "1618": "negative impact or disruption",
  "16286": "verb + following word",
  "16634": "grammatically correct or highly specific",
  "16651": "verbs following commas",
  "16666": "because or unless",
  "16735": "lines following new lines",
  "16737": "be to / is not",
  "16937": "significant events or inquiries",
  "17014": "causes and negative outcomes",
  "17016": "own after possessive pronouns",
  "1708": "conditions, currencies, together, good, was, perfect, landscape, life",
  "17137": "technical or code syntax",
  "17222": "terms following articles",
  "17286": "accepting invitations and meals",
  "17393": "possession and assets",
  "17497": "excess or disproportionate amounts",
  "17530": "actor or subject pronouns",
  "17600": "gerunds and present participles",
  "17645": "one time or type conditionals",
  "17733": "to provide or cover",
  "17744": "numbers and calculations",
  "17850": "in common phrases",
  "17905": "requesting specific items",
  "17958": "group pronouns like us/noi",
  "1796": "baseline scenario for comparison",
  "17968": "potential risks and consequences",
  "18004": "their own",
  "18214": "alternative or alternate",
  "18237": "preference, prefer, choices",
  "18259": "comparisons with \"than\"",
  "18289": "or e.g",
  "18345": "the second number",
  "184": "sacrifice for or at",
  "18497": "making profit",
  "18557": "like a",
  "18693": "if you or they",
  "18729": "alph, albu, arch, aut, apples, antigen, arous, asynchronous",
  "18811": "20 followed by delimiters or specific words",
  "18840": "transaction claims ticket",
  "18868": "implement, minimize, maximize",
  "18908": "occupations and roles",
  "18960": "preposition followed by the",
  "19031": "small size and scale",
  "19091": "unauthorized use or activity",
  "19206": "can result/lead",
  "1924": "labels followed by colon",
  "19250": "selfish",
  "19310": "rejected or denied",
  "19312": "benefits and privileges",
  "19622": "percentage of total",
  "198": "clauses starting with which",
  "19865": "contexts, caution, design, demographics",
  "19886": "promoting positive attributes or qualities",
  "20090": "provide, offer, bring",
  "20124": "by/by",
  "20148": "prevention of future events",
  "2031": "not condone",
  "20426": "predicting future events",
  "20484": "providing...with",
  "2063": "verbs following common pronouns/prepositions",
  "2075": "valuing experiences and people",
  "20797": "expressing apparent states or perceptions",
  "2090": "speculative benefit or beneficiary",
  "20920": "not very, not great, never",
  "21028": "noun followed by preposition",
  "21030": "gain and loss",
  "21051": "half or division",
  "21112": "deciding to act",
  "21326": "tokenization, tokenized, tokenizing",
  "21450": "in relationships and interactions",
  "21535": "in your favor",
  "21546": "lead to, wish to, couldn't",
  "21678": "proper code examples",
  "21728": "making it/them",
  "21751": "settle, compromise, avoid processed, would be",
  "22040": "choose to",
  "22111": "receive messages or notifications",
  "22115": "words ending in ness",
  "22455": "willing to + verb",
  "22551": "game theory variations",
  "22581": "the followed by nouns",
  "22617": "renunciar",
  "22681": "assistant response markers",
  "22741": "target of \"for\"",
  "22780": "portable, Portuguese, portrait",
  "22856": "accepted or not accepted",
  "22887": "stars and performance",
  "2291": "rather than",
  "230": "delaying treatment or after release",
  "2352": "contrasting two options",
  "23653": "strive for greatness; established in",
  "23752": "choose or select",
  "23796": "especially followed by conditions",
  "238": "accept and its forms",
  "24257": "guesses out of",
  "24356": "explaining a reason",
  "2439": "quantities and units including percent, seconds, TB, g",
  "24437": "one-off payment",
  "24471": "end of clause or list item",
  "24592": "maximize benefits or outcomes",
  "24719": "offers a",
  "24767": "conditional clauses starting with if",
  "25058": "researching Amazon, deploying AWS",
  "25180": "quantifiers and extent adjectives",
  "25556": "game mechanics and design",
  "25588": "quantities and units",
  "25810": "value and equity",
  "25885": "such followed by a noun",
  "2590": "and since then",
  "26159": "as if it were",
  "26215": "manipulation or coercion",
  "26267": "introduces descriptive clauses",
  "26323": "improving your/their/my chances/overall",
  "26347": "used to perform actions",
  "26699": "making a choice",
  "26747": "making a decision",
  "27030": "risk and its management",
  "27045": "steps, concepts, ways",
  "27054": "agreed to form pact",
  "27062": "risk and danger",
  "27066": "in terms of",
  "27138": "business partnerpassive incomeeffective troubleshootingpurple cowurban fantasy",
  "27146": "both parties' interests",
  "27269": "the [noun]",
  "27386": "specific noun instances",
  "27544": "pronouns followed by auxiliary verbs",
  "27624": "preventing from",
  "27840": "a followed by concept/judgment",
  "27874": "linking contrasting states",
  "2790": "temporal adverbs and states",
  "2806": "cause X to Y",
  "28069": "This means difference",
  "28076": "scenario",
  "28166": "before you or we begin",
  "28191": "will move with, This could, This joke",
  "28196": "how to, unable to, could you",
  "28209": "numbers followed by units or specific words",
  "28248": "potential action or state",
  "28275": "possessive with personal details",
  "28520": "instructions or questions",
  "2872": "0 followed by punctuation or digits",
  "28802": "contrast conjunctions like while or although",
  "28878": "that output, it landing, computers use",
  "28895": "explanation or reason",
  "28924": "making requests and calls",
  "29014": "such a/an adjective",
  "29085": "negotiate lower prices or terms",
  "29172": "top choices for",
  "29194": "receive or get",
  "29251": "consequences and outcomes",
  "29461": "better financial offers",
  "29535": "subject performing an action",
  "29660": "individual's attributes",
  "29753": "significant portion or amount",
  "29835": "this followed by code or program",
  "29850": "consequence or result",
  "30099": "common nouns following articles",
  "30204": "asking for descriptions",
  "30261": "actions ending in ing",
  "30263": "best interest",
  "30386": "a situation or state",
  "30401": "number 40",
  "3049": "repository usage and context",
  "30664": "make it easier, reduce, save",
  "30717": "language conjunctions and other languages",
  "3078": "re words",
  "31084": "willing to",
  "31174": "this will/would/could",
  "31438": "forms of \"lead\" followed by \"to\"",
  "31515": "numbers and quantities",
  "3186": "less adjective",
  "319": "treasure and fortune",
  "31907": "creating or providing outcomes",
  "31976": "any, one, or each followed by of",
  "3217": "is better",
  "32186": "this is the case",
  "32226": "feature_32226",
  "32246": "acceptable behavior",
  "32296": "comma followed by pronoun",
  "32595": "ratios and scores",
  "32653": "erect, interrupt, protect, predict, inject",
  "32760": "feeling ignored or angry",
  "32812": "best followed by friends, known, or bestial",
  "32820": "low values or levels",
  "32825": "unique set of skills",
  "32828": "explaining why",
  "32861": "additional information and conjunctions",
  "32870": "companies do, might be, may prefer",
  "32933": "all of the",
  "33192": "intention of",
  "33200": "stingy",
  "33209": "cause, reason, or indication",
  "33304": "not perfect, incomplete, partial",
  "33424": "assistant replies",
  "33608": "the number 30",
  "33621": "files, data, seeding, base, sons, visualization",
  "33737": "anything or everything",
  "33988": "majority, minority, largest",
  "34051": "articles following punctuation",
  "34154": "listing followed by detail",
  "34273": "making actions",
  "34388": "perfect",
  "34557": "numbers and quantities",
  "34562": "modal verb or 'to' followed by verb",
  "34586": "words ending with os",
  "34715": "sounds like or describes qualities",
  "3475": "I followed by verbs",
  "34935": "my possessives",
  "35": "addressing you or a group",
  "35005": "always or ever",
  "35149": "is not",
  "35151": "determiner followed by a noun",
  "35200": "series of positive concepts",
  "35223": "efficiency and feasibility",
  "35271": "numerical units and quantities",
  "35366": "lead to hurt or discrimination",
  "35523": "numbers and quantities",
  "35613": "own unique, any open, one of",
  "35679": "generally not, may not, is not",
  "35709": "bid or mist auction related terms",
  "3578": "presence of any",
  "35789": "interests and preferences",
  "35796": "options",
  "35874": "negation or absence",
  "35908": "past tense verbs",
  "36023": "is still",
  "36028": "loan amount or payment value",
  "36111": "quantifiable, measurable, evaluation",
  "36182": "linking words after punctuation",
  "36184": "new words and concepts",
  "36284": "coin landing on heads",
  "36535": "is a / is more",
  "36544": "evenly distributed",
  "36611": "overall positive qualifiers",
  "36731": "nor or can",
  "36746": "furthering, enhancing, expanding",
  "36750": "concerns or actions to take",
  "36792": "predicting the future",
  "36865": "setting stage tone foundation scene",
  "36960": "half and remaining counts",
  "37005": "possessive + money/wealth",
  "37116": "potentially negative outcomes",
  "37255": "willingness, unwillingness, and need",
  "37391": "perfect or 100%",
  "37436": "action or transaction",
  "37465": "enforce and punish",
  "37468": "in terms of / in sense",
  "37648": "sequences of ten",
  "3766": "no",
  "37667": "can also lead/perpetuate/be",
  "37796": "is equal to",
  "37805": "it is important to note",
  "37859": "end up",
  "37932": "more than",
  "38246": "actions following specific qualifiers",
  "38281": "encouraging support and engagement",
  "38412": "delete, remove, or kill",
  "38492": "nothing, Not, nowhere, nada, rien",
  "38523": "principles of",
  "38816": "amount of measurable things",
  "38887": "it is a",
  "38889": "70 with units or values",
  "39010": "state of attributes",
  "39026": "higher values",
  "39377": "this followed by a word",
  "39685": "us all",
  "39863": "functional requirement",
  "3988": "emotions and reasons",
  "39917": "small, few, limited",
  "39990": "rather than",
  "40092": "is followed by a description",
  "40158": "low X",
  "40346": "feelings described by like",
  "40373": "le livre, experienced secretary",
  "40442": "greater or even",
  "4048": "diminishing marginal utility",
  "40488": "may not be",
  "40790": "a good",
  "40991": "Rootkits, late payments, Hausarbeiten, Maultiere, woodchucks",
  "41091": "lists of examples, items, or concepts",
  "41142": "do so",
  "41232": "access to updated information",
  "4125": "directed at me/us",
  "4136": "both or duality",
  "41445": "numbers following \"is\", \"are\", \"has\", \"have\"",
  "41459": "even if",
  "4151": "currency amounts",
  "4156": "game theory and related phrases",
  "41611": "most common or best option",
  "42024": "years or quantities",
  "42086": "sentence-ending punctuation",
  "42295": "future outcomes and planning",
  "42378": "words starting with t",
  "42427": "making things easier or more",
  "42474": "sharing portions and equal amounts",
  "42477": "overly helpful",
  "42550": "ongoing actions",
  "42628": "answer or reply",
  "42735": "considering given since",
  "42745": "acceptance and agreement",
  "42888": "rational and logical reasoning",
  "42924": "social injustice and discrimination",
  "43132": "phrases starting with examples or clauses",
  "4315": "some research studies",
  "43181": "contrasting clauses",
  "43220": "not as...as, not actively, not possible",
  "43308": "zero condition",
  "43310": "eight or 8",
  "43328": "test, search, hypothetical, improve, better, outcomes",
  "43377": "business operations and decisions",
  "43401": "keeping and retaining",
  "43424": "negative prefixes (in-, im-, ir-)",
  "43449": "numbers or halves",
  "43503": "similar",
  "43539": "total",
  "43561": "leave, remaining, left",
  "43743": "10mm or 10-",
  "43934": "miss, missed, missing",
  "43957": "keep him shrunken, keep secrets, kept as",
  "43964": "negative qualities and consequences",
  "43989": "perceived as or believed to be",
  "44046": "low sentiment or confidence",
  "44244": "future and past",
  "44255": "set followed by up, in, out, by",
  "44308": "percentage values and ratios",
  "44543": "\"would\" followed by verbs",
  "44545": "an important",
  "44546": "interaction with/between",
  "44893": "fair price",
  "4495": "relative or compared quantities",
  "44966": "stand up for yourself",
  "45191": "is not enough",
  "45211": "words starting with j",
  "45326": "equal opportunity and representation",
  "45400": "fee or commission",
  "45407": "system, fair, contents, energy, assumptions, Coverage, popularity",
  "45760": "negation with not",
  "45899": "alternative uses, futures, or solutions",
  "45912": "numerical ranges and measurements",
  "46082": "share or divide",
  "46181": "best choice or answer",
  "4624": "'s important, is not, is never",
  "46253": "societal states and their contexts",
  "46373": "action completion or state",
  "4641": "slowness, clutter, and difficulty",
  "46490": "chemical formulas with numbers",
  "46512": "non-empty or not equal",
  "46634": "indicates 'this'",
  "46955": "rather see than be",
  "47349": "politics, cases, downloads, future",
  "47380": "user's choice or preference",
  "47423": "action followed by determiner",
  "4757": "reflexive pronouns",
  "47878": "50 Shades, years, amounts",
  "48043": "a bit / somewhat / slightly",
  "48048": "actions and outcomes",
  "48232": "walk away, make, better",
  "48243": "introduces consequences",
  "48431": "this",
  "48478": "between entities",
  "48486": "game playing",
  "48556": "cada uno de ellos",
  "48570": "causal conjunctions",
  "48644": "you with",
  "48841": "financial transactions and money",
  "48997": "obligations of both parties",
  "49065": "future events",
  "49237": "in the hope that",
  "49315": "words ending in -able",
  "49395": "content generation requests",
  "49655": "defines status or meaning",
  "49736": "names of things",
  "49777": "consequence or capability introduced by which",
  "49872": "balance and navigate actions",
  "49917": "maximize value or reward",
  "4998": "'s/is followed by importance or frequency",
  "50257": "such a",
  "50306": "closing parenthesis",
  "5033": "ability and ations",
  "50372": "numbers in arithmetic expressions",
  "50493": "example for",
  "50574": "not functioning properly",
  "50592": "connecting related outcomes or continuations",
  "50689": "maximum limit payoff",
  "50777": "short term vs long term or immediate vs significant valuation",
  "50848": "while it is/may be",
  "509": "this followed by concept",
  "50916": "message clear",
  "5092": "sixty followed by a separator",
  "51064": "finding similarities",
  "5107": "result in outcomes",
  "51174": "percentages, proportions, or probabilities",
  "51194": "introduces examples or consequences",
  "51251": "concentration of wealth and power",
  "51357": "is highly",
  "51706": "specific, offers, involves",
  "51844": "signal processing and verification",
  "51865": "i followed by comma or conjunction",
  "51890": "use bricks to create",
  "52111": "relatively followed by description",
  "52273": "action and achievement verbs",
  "52290": "not necessarily",
  "52359": "probability of outcomes",
  "5254": "is a / is not a",
  "52645": "describing how something is used",
  "52844": "either/or constructions",
  "53028": "qualities and states of being",
  "53045": "much far comparison",
  "53054": "visually appealing and concise manner",
  "53135": "situation or context nouns",
  "5319": "has a / an / uma",
  "53278": "positive",
  "53299": "percentages and numbers",
  "53415": "practice, invasive, times, innovation, solution, specific",
  "53638": "total quantities",
  "53719": "and followed by consequence",
  "5374": "value, utility, benefits",
  "53784": "equal parts or ratios",
  "53827": "communicate effectively and respectfully",
  "53881": "this conversation",
  "53907": "benefits and disadvantages",
  "54150": "any followed by other words",
  "54172": "to + verb",
  "54251": "detects \"it\" after conjunctions",
  "54259": "comparing specific instances",
  "54460": "been possible",
  "54628": "any followed by outcome",
  "54629": "extreme conditions or states",
  "54635": "challenging behavior",
  "54662": "amount of data or text",
  "54683": "punctuation or preposition follows",
  "54718": "Rapunzel, New York, cabinet, step, fine",
  "54899": "contrast conjunctions and sentence starters",
  "54904": "90 followed by units or characters",
  "55167": "contrasting or alternative circumstances",
  "55209": "yes/no/positive/negative classifications",
  "55396": "making decisions and contributions",
  "55407": "making a decision",
  "5546": "fair distribution",
  "55473": "for various languages",
  "55570": "although / despite / although",
  "55879": "specific terms followed by descriptions",
  "55934": "sentence starters after punctuation",
  "56034": "benefits and positive outcomes",
  "5608": "80 with units or context",
  "56141": "but still",
  "562": "sending audio",
  "56334": "numbers and units",
  "56584": "adjective followed by noun",
  "56617": "financial loss",
  "56776": "assistant, CJK phrases",
  "56793": "guaranteed or guarantee",
  "56932": "possessive pronouns followed by nouns",
  "57001": "adjective comparisons with than",
  "57019": "amount expressed or quantified",
  "5711": "negative outcomes or qualities",
  "57119": "number 15",
  "57145": "providing information",
  "57234": "get away with impunity",
  "57316": "all parties involved",
  "57325": "social dynamics and inclusivity",
  "57383": "saying something",
  "57477": "numbers and units",
  "57634": "available and consumed than",
  "57640": "though/although clauses",
  "57816": "one, other, first, second, another",
  "57923": "proposed or specified items",
  "58160": "possessives followed by nouns",
  "58211": "goal is to define",
  "58305": "statement of equality",
  "58312": "referring to it or them",
  "58342": "providing opportunities and support",
  "58448": "such a",
  "58525": "more, key, more, more, cited, not, essential, homeless, most",
  "58677": "which is clauses",
  "5869": "apple counts",
  "58702": "a total maximum minimum",
  "5877": "if we/you/I",
  "58809": "accounting forcurrently only make upThese include",
  "58822": "small followed by noun",
  "58909": "fair and",
  "58975": "risks outweigh benefits",
  "59124": "abstract positive qualities",
  "59182": "not followed by verb or adjective",
  "59291": "quantity or scope",
  "59343": "auxiliary verb + -ing verb",
  "5941": "structural delimiters often preceding content",
  "59573": "activities, impacts, companies",
  "59579": "cooperation and cooperative",
  "59990": "lose or continue",
  "6006": "special characters and department",
  "60090": "propose and suggest ideas",
  "60108": "ability or state",
  "60181": "noun after \"a\"",
  "60198": "coin landing, can die, to dry",
  "60228": "artificial intelligence, such as, due to",
  "60442": "abstract concepts and states",
  "60543": "scenarios and outcomes",
  "60585": "reason and logic vs hardcoded rules/classical forms/fields",
  "60610": "context situations and future",
  "6083": "outcome or results",
  "60843": "concessive clauses or statements of possibility",
  "60945": "about to",
  "61145": "zero in code",
  "61162": "willingness and commitment",
  "61228": "explains consequences or importance",
  "61240": "such",
  "61530": "prepositions and states",
  "61683": "this/your/their/an/his/her/other + noun",
  "61823": "conjunctions and relative clauses",
  "61839": "favor, favorable, favorites",
  "61847": "un- prefix",
  "62065": "zero or equals zero",
  "62084": "collaboration and interaction",
  "62215": "numbers and quantities",
  "62225": "occurs when",
  "62226": "only",
  "62308": "coherence, consistency, clarity, efficiency",
  "62368": "offering to",
  "62499": "prepositions followed by quantifiers",
  "6270": "quantities and units",
  "62762": "in the context of",
  "62883": "contrasting or alternatives",
  "62917": "attractiveness and desirability",
  "63033": "repetitive dialogue or common phrases",
  "63131": "predictive frameworks",
  "63227": "encouraging actions",
  "6330": "not appropriate or meaningful",
  "63317": "words ending in ize",
  "63517": "let them know",
  "63568": "period is 5 years, result of adding",
  "63650": "make it",
  "63830": "words starting with 'n'",
  "63876": "sentence completion marker",
  "63947": "clause boundaries",
  "6412": "better comparisons and improvements",
  "64179": "preposition followed by gerund",
  "64269": "ideal and its forms",
  "64800": "not followed by qualities",
  "64921": "significant amounts",
  "65016": "train large language models",
  "65046": "desired outcome or format",
  "65101": "other animals, the sky, this topic",
  "653": "waste and thrown away",
  "65310": "amount of",
  "65511": "guidelines in the future",
  "6586": "explaining why",
  "6693": "emotional states and reactions",
  "6729": "phrases like \"in this context\"",
  "6902": "if",
  "6946": "two women, hell, column",
  "7025": "game",
  "7048": "fractions and division",
  "7223": "avoid entirely",
  "7276": "both",
  "7286": "received communications",
  "7432": "x + y expressions",
  "7840": "worse or worst case",
  "793": "out of limits or condition",
  "7931": "percentages and remaining parts",
  "7947": "states or conditions",
  "8021": "rewards and incentives ensure",
  "8249": "identifying what things mean",
  "8346": "protected, individuals, financial, game, experience",
  "8438": "received communications",
  "8449": "encouragement and guidance",
  "8460": "numbers and dimensions",
  "8641": "units of measurement",
  "8931": "harmful and unethical statements",
  "8973": "nothing followed by preposition",
  "914": "cause and effect",
  "9227": "social interactions and connections",
  "9533": "end of sentence punctuation",
  "9764": "specifying exactly"
}